astraeus/__init__.py
astraeus/constants.py
astraeus/interval.py
astraeus/orbit.py
astraeus/body/__init__.py
astraeus/body/base_body.py
astraeus/body/body.py
astraeus/body/earth.py
astraeus/body/enum.py
astraeus/frame/__init__.py
astraeus/frame/base_frame_enum.py
astraeus/frame/frame.py
astraeus/integrator/__init__.py
astraeus/integrator/integrator.py
astraeus/integrator/runge_kutta.py
astraeus/perturbation/__init__.py
astraeus/perturbation/gravity_perturbation.py
astraeus/perturbation/perturbation.py
astraeus/propogate/__init__.py
astraeus/propogate/propagate.py
tests/__init__.py
tests/integrator/__init__.py
tests/integrator/test_runge_kutta_4.py
tests/perturbation/__init__.py
tests/perturbation/test_gravity_perturbation.py
tests/propogation/__init__.py
tests/propogation/test_earth_two_body.py
astraeus-0.0.1.dist-info/LICENSE.md
astraeus-0.0.1.dist-info/METADATA
astraeus-0.0.1.dist-info/WHEEL
astraeus-0.0.1.dist-info/top_level.txt
astraeus-0.0.1.dist-info/RECORD
