Metadata-Version: 2.1
Name: astraeus
Version: 0.0.1
Summary: Orbit Propogation and Numeric Integration
Home-page: https://github.com/Delaney7340/astraeus
Author: Joseph Delaney
Classifier: Programming Language :: Python :: 3
Classifier: License :: OSI Approved :: MIT License
Classifier: Operating System :: OS Independent
License-File: LICENSE.md
Requires-Dist: astropy
Requires-Dist: numpy
Requires-Dist: portion
Requires-Dist: tqdm
